{
	"info": {
		"_postman_id": "7450a74d-96af-4dc6-af57-60355ac5b33e",
		"name": "API AUTOMATION",
		"schema": "https://schema.getpostman.com/json/collection/v2.1.0/collection.json",
		"_exporter_id": "49186496"
	},
	"item": [
		{
			"name": "GET",
			"event": [
				{
					"listen": "test",
					"script": {
						"exec": [
							"const schema = {\r",
							"  type: \"object\",\r",
							"  properties: {\r",
							"    data: {\r",
							"      type: \"object\",\r",
							"      properties: {\r",
							"        id: { type: \"number\" },\r",
							"        email: { type: \"string\" },\r",
							"        first_name: { type: \"string\" },\r",
							"        last_name: { type: \"string\" }\r",
							"      },\r",
							"      required: [\"id\",\"email\",\"first_name\",\"last_name\"]\r",
							"    }\r",
							"  },\r",
							"  required: [\"data\"]\r",
							"};\r",
							"\r",
							"\r",
							"\r",
							"pm.test(\"Status code is 200\", function(){\r",
							"  pm.response.to.have.status(200);\r",
							"});\r",
							"\r",
							"pm.test(\"Response matches JSON schema\", function(){\r",
							"  pm.response.to.have.jsonSchema(schema);\r",
							"});\r",
							""
						],
						"type": "text/javascript",
						"packages": {},
						"requests": {}
					}
				}
			],
			"request": {
				"method": "GET",
				"header": [],
				"url": {
					"raw": "https://reqres.in/api/users/2",
					"protocol": "https",
					"host": [
						"reqres",
						"in"
					],
					"path": [
						"api",
						"users",
						"2"
					]
				}
			},
			"response": []
		},
		{
			"name": "POST",
			"event": [
				{
					"listen": "test",
					"script": {
						"exec": [
							"const schema = {\r",
							"  type: \"object\",\r",
							"  properties: {\r",
							"    nama: { type: \"string\" },\r",
							"    pekerjaan : { type: \"string\" },\r",
							"    id: { type: \"string\" },\r",
							"    createdAt: { type: \"string\" }\r",
							"  },\r",
							"  required: [\"nama\",\"pekerjaan\",\"id\",\"createdAt\"]\r",
							"};\r",
							"\r",
							"pm.test(\"Successful POST request\", function () {\r",
							"    pm.expect(pm.response.code).to.be.oneOf([201, 202]);\r",
							"});\r",
							"\r",
							"pm.test(\"Status code is 201\", function(){\r",
							"  pm.response.to.have.status(201);\r",
							"});\r",
							"\r",
							"pm.test(\"Response matches JSON schema\", function(){\r",
							"  pm.response.to.have.jsonSchema(schema);\r",
							"});\r",
							""
						],
						"type": "text/javascript",
						"packages": {},
						"requests": {}
					}
				}
			],
			"request": {
				"method": "POST",
				"header": [
					{
						"key": "x-api-key",
						"value": "reqres-free-v1",
						"type": "text"
					},
					{
						"key": "Content-Type",
						"value": "application/json",
						"type": "text"
					}
				],
				"body": {
					"mode": "raw",
					"raw": "{\r\n  \"nama\": \"Valent\",\r\n  \"pekerjaan\": \"QA Tester\"\r\n}\r\n",
					"options": {
						"raw": {
							"language": "json"
						}
					}
				},
				"url": {
					"raw": "https://reqres.in/api/users",
					"protocol": "https",
					"host": [
						"reqres",
						"in"
					],
					"path": [
						"api",
						"users"
					]
				}
			},
			"response": []
		},
		{
			"name": "PATCH",
			"event": [
				{
					"listen": "test",
					"script": {
						"exec": [
							"const schema = {\r",
							"  type: \"object\",\r",
							"  properties: {\r",
							"    nama: { type: \"string\" },\r",
							"    pekerjaan : { type: \"string\" },\r",
							"    id: { type: \"string\" },\r",
							"    createdAt: { type: \"string\" }\r",
							"  },\r",
							"  required: [\"nama\",\"pekerjaan\",\"id\",\"createdAt\"]\r",
							"};\r",
							"\r",
							"pm.test(\"Status code is 200\", function(){\r",
							"  pm.response.to.have.status(200);\r",
							"});\r",
							"\r",
							"pm.globals.get(\"variable_key\");\r",
							"\r",
							"pm.test(\"Response matches JSON schema\", function(){\r",
							"  pm.response.to.have.jsonSchema(schema);\r",
							"});\r",
							""
						],
						"type": "text/javascript",
						"packages": {},
						"requests": {}
					}
				}
			],
			"request": {
				"method": "PATCH",
				"header": [
					{
						"key": "x-api-key",
						"value": "reqres-free-v1",
						"type": "text"
					}
				],
				"body": {
					"mode": "raw",
					"raw": "{\r\n    \"pekerjaan\": \"QA Manager\"\r\n}",
					"options": {
						"raw": {
							"language": "json"
						}
					}
				},
				"url": {
					"raw": "https://reqres.in/api/users/2",
					"protocol": "https",
					"host": [
						"reqres",
						"in"
					],
					"path": [
						"api",
						"users",
						"2"
					]
				}
			},
			"response": []
		},
		{
			"name": "DELETE",
			"event": [
				{
					"listen": "test",
					"script": {
						"exec": [
							"pm.test(\"Status code is 204\", function(){\r",
							"  pm.response.to.have.status(204);\r",
							"});\r",
							""
						],
						"type": "text/javascript",
						"packages": {},
						"requests": {}
					}
				}
			],
			"request": {
				"method": "DELETE",
				"header": [
					{
						"key": "x-api-key",
						"value": "reqres-free-v1",
						"type": "text"
					},
					{
						"key": "Content-Type",
						"value": "application/json",
						"type": "text"
					}
				],
				"body": {
					"mode": "raw",
					"raw": "",
					"options": {
						"raw": {
							"language": "json"
						}
					}
				},
				"url": {
					"raw": "https://reqres.in/api/users/2",
					"protocol": "https",
					"host": [
						"reqres",
						"in"
					],
					"path": [
						"api",
						"users",
						"2"
					]
				}
			},
			"response": []
		}
	]
}